README.txt
setup.cfg
setup.py
eggchecker/__init__.py
eggchecker/runflakes.py
eggchecker/runtests.py
eggchecker.egg-info/PKG-INFO
eggchecker.egg-info/SOURCES.txt
eggchecker.egg-info/dependency_links.txt
eggchecker.egg-info/entry_points.txt
eggchecker.egg-info/not-zip-safe
eggchecker.egg-info/requires.txt
eggchecker.egg-info/top_level.txt
