Metadata-Version: 1.0
Name: eggchecker
Version: 0.1.3dev
Summary: setuptools command extensions to run QA and tests on the code
Home-page: http://hg.programmation-python.org
Author: Tarek Ziade
Author-email: tarek@ziade.org
License: GPL
Keywords: qa pylintrc
Platform: UNKNOWN
